{
	"ImportPath": "github.com/shiguredo/fuji",
	"GoVersion": "go1.5.1",
	"Deps": [
		{
			"ImportPath": "git.eclipse.org/gitroot/paho/org.eclipse.paho.mqtt.golang.git",
			"Comment": "v0.9.1-14-g546c47a",
			"Rev": "546c47a6d0e9492e77f6f37473d59c36a708e08b"
		},
		{
			"ImportPath": "github.com/Sirupsen/logrus",
			"Comment": "v0.7.1",
			"Rev": "3fc34d061b9c78a70db853c7cb6b0576b6d4f32d"
		},
		{
			"ImportPath": "github.com/codegangsta/cli",
			"Comment": "1.2.0-95-g9b2bd2b",
			"Rev": "9b2bd2b3489748d4d0a204fa4eb2ee9e89e0ebc6"
		},
		{
			"ImportPath": "github.com/go-ini/ini",
			"Comment": "v0-16-g1772191",
			"Rev": "177219109c97e7920c933e21c9b25f874357b237"
		},
		{
			"ImportPath": "github.com/pborman/uuid",
			"Rev": "ca53cad383cad2479bbba7f7a1a05797ec1386e4"
		},
		{
			"ImportPath": "github.com/shirou/gopsutil/cpu",
			"Comment": "1.0.0-160-g82a76c0",
			"Rev": "82a76c01e3af444ce144b30f228467976ef75864"
		},
		{
			"ImportPath": "github.com/shirou/gopsutil/mem",
			"Comment": "1.0.0-160-g82a76c0",
			"Rev": "82a76c01e3af444ce144b30f228467976ef75864"
		},
		{
			"ImportPath": "github.com/tarm/serial",
			"Rev": "e3f4c97bb7137112ddfc06cc44a939e45f41d941"
		},
		{
			"ImportPath": "golang.org/x/net/websocket",
			"Rev": "db8e4de5b2d6653f66aea53094624468caad15d2"
		},
		{
			"ImportPath": "github.com/stretchr/testify/assert",
			"Rev": "59fc8e570cd707a33a93842b00a9aae4b5cd38b2"
		},
		{
			"ImportPath": "gopkg.in/validator.v2",
			"Rev": "8e445b9dc14ab1a1a78cc1f712df991307173ee6"
		}
	]
}
